MANIFEST.in
setup.py
Absinthe.egg-info/PKG-INFO
Absinthe.egg-info/SOURCES.txt
Absinthe.egg-info/dependency_links.txt
Absinthe.egg-info/requires.txt
Absinthe.egg-info/top_level.txt
absinthe/__init__.py
absinthe/absinthe_client.py
absinthe/absinthe_server.py
absinthe/config_example.json
absinthe/editors.py
absinthe/message.py
absinthe/server_listen.py
absinthe/tools/__init__.py
absinthe/tools/background_process_handler.py
absinthe/tools/cliargumentstreeparser.py
absinthe/tools/commands.py
absinthe/tools/config.py
absinthe/tools/daemon.py
absinthe/tools/logger.py
absinthe/tools/remote_process_base.py
absinthe/tools/remote_process_manager.py
absinthe/tools/service.py
absinthe/tools/service_manager.py
absinthe/tools/timer.py
absinthe/tools/utils.py
absinthe/tools/window_manager.py
absinthe/tools/linux/__init__.py
absinthe/tools/linux/service.py
absinthe/tools/linux/service_manager.py
absinthe/tools/linux/window_manager.py
absinthe/tools/win/__init__.py
absinthe/tools/win/service.py
absinthe/tools/win/service_manager.py
absinthe/tools/win/window_manager.py
bin/abs
bin/absinthe