Metadata-Version: 1.0
Name: Absinthe
Version: 1.0.0
Summary: A tiny server(-client) app to open sshfs connected files over ssh in any local editor
Home-page: https://github.com/voidpp/absinthe
Author: Lajos Santa
Author-email: santa.lajos@coldline.hu
License: MIT
Platform: UNKNOWN
